BigPig/__init__.py
BigPig/oh_pig.py
whrtest-0.0.1.dist-info/LICENSE
whrtest-0.0.1.dist-info/METADATA
whrtest-0.0.1.dist-info/WHEEL
whrtest-0.0.1.dist-info/top_level.txt
whrtest-0.0.1.dist-info/RECORD
