Metadata-Version: 2.1
Name: whrtest
Version: 0.0.1
Summary: Oh! whr
Home-page: https://github.com/BigGoby/BigPig
Author: A Big Boby
Author-email: ilikepython@163.com
License: UNKNOWN
Platform: UNKNOWN
Classifier: Programming Language :: Python :: 3
Classifier: License :: OSI Approved :: MIT License
Classifier: Operating System :: OS Independent
License-File: LICENSE
